{
  "theme": {
    "$type": "theme",
    "$value": "snow",
    "$description": "Pure white with subtle gray - the cleanest, most minimal"
  },
  "color": {
    "text": {
      "default": {
        "$type": "color",
        "$value": "oklch(21.0% 0.006 285.9)",
        "$description": "Primary text on light surfaces - near black",
        "$originalHex": "#18181B"
      },
      "muted": {
        "$type": "color",
        "$value": "oklch(55.2% 0.014 285.9)",
        "$description": "Secondary text - neutral gray",
        "$originalHex": "#71717A"
      },
      "inverted": {
        "$type": "color",
        "$value": "oklch(100.0% 0.000 0.0)",
        "$description": "Text color for dark surfaces - pure white",
        "$originalHex": "#FFFFFF"
      },
      "link": {
        "$type": "color",
        "$value": "oklch(62.3% 0.188 259.8)",
        "$description": "Link text color - neutral blue",
        "$originalHex": "#3B82F6"
      },
      "link.hover": {
        "$type": "color",
        "$value": "oklch(54.6% 0.215 262.9)",
        "$description": "Link text color on hover - deeper blue",
        "$originalHex": "#2563EB"
      }
    },
    "surface": {
      "default": {
        "$type": "color",
        "$value": "oklch(100.0% 0.000 0.0)",
        "$description": "Default surface background - pure white",
        "$originalHex": "#FFFFFF"
      },
      "raised": {
        "$type": "color",
        "$value": "oklch(98.5% 0.000 0.0)",
        "$description": "Elevated surface background - near-white gray",
        "$originalHex": "#FAFAFA"
      },
      "sunken": {
        "$type": "color",
        "$value": "oklch(96.7% 0.001 286.4)",
        "$description": "Depressed surface background - very light gray for inputs",
        "$originalHex": "#F4F4F5"
      },
      "overlay": {
        "$type": "color",
        "$value": "rgba(0, 0, 0, 0.4)",
        "$description": "Overlay background for modals - semi-transparent black"
      }
    },
    "border": {
      "default": {
        "$type": "color",
        "$value": "oklch(92.0% 0.004 286.3)",
        "$description": "Default border color - neutral light gray",
        "$originalHex": "#E4E4E7"
      },
      "subtle": {
        "$type": "color",
        "$value": "oklch(96.7% 0.001 286.4)",
        "$description": "Subtle border for dividers - very faint gray",
        "$originalHex": "#F4F4F5"
      },
      "strong": {
        "$type": "color",
        "$value": "oklch(71.2% 0.013 286.1)",
        "$description": "Stronger border for emphasis - medium gray",
        "$originalHex": "#A1A1AA"
      }
    },
    "interactive": {
      "primary": {
        "$type": "color",
        "$value": "oklch(62.3% 0.188 259.8)",
        "$description": "Primary interactive element color - blue",
        "$originalHex": "#3B82F6"
      },
      "primary.hover": {
        "$type": "color",
        "$value": "oklch(54.6% 0.215 262.9)",
        "$description": "Primary interactive color on hover - deeper blue",
        "$originalHex": "#2563EB"
      },
      "secondary": {
        "$type": "color",
        "$value": "oklch(55.2% 0.014 285.9)",
        "$description": "Secondary interactive element color - neutral gray",
        "$originalHex": "#71717A"
      }
    },
    "focus": {
      "ring": {
        "$type": "color",
        "$value": "oklch(71.4% 0.143 254.6)",
        "$description": "Focus ring outline color - light blue glow",
        "$originalHex": "#60A5FA"
      }
    },
    "status": {
      "success": {
        "$type": "color",
        "$value": "oklch(62.7% 0.170 149.2)",
        "$description": "Success state color - green",
        "$originalHex": "#16A34A"
      },
      "warning": {
        "$type": "color",
        "$value": "oklch(68.1% 0.142 75.8)",
        "$description": "Warning state color - yellow",
        "$originalHex": "#CA8A04"
      },
      "error": {
        "$type": "color",
        "$value": "oklch(57.7% 0.215 27.3)",
        "$description": "Error state color - red",
        "$originalHex": "#DC2626"
      },
      "info": {
        "$type": "color",
        "$value": "oklch(62.3% 0.188 259.8)",
        "$description": "Info state color - blue",
        "$originalHex": "#3B82F6"
      }
    }
  },
  "shadow": {
    "card": {
      "$type": "shadow",
      "$value": "0 4px 6px -1px rgba(0, 0, 0, 0.04), 0 2px 4px -2px rgba(0, 0, 0, 0.02)",
      "$description": "Card elevation shadow - minimal neutral shadow"
    },
    "dropdown": {
      "$type": "shadow",
      "$value": "0 10px 15px -3px rgba(0, 0, 0, 0.06), 0 4px 6px -4px rgba(0, 0, 0, 0.04)",
      "$description": "Dropdown menu elevation shadow - minimal shadow"
    },
    "modal": {
      "$type": "shadow",
      "$value": "0 20px 25px -5px rgba(0, 0, 0, 0.08), 0 8px 10px -6px rgba(0, 0, 0, 0.06)",
      "$description": "Modal dialog elevation shadow - minimal shadow"
    },
    "focus": {
      "$type": "shadow",
      "$value": "0 0 0 3px rgba(59, 130, 246, 0.3)",
      "$description": "Focus ring glow shadow - blue glow ring"
    }
  }
}